{"stat.killEntity.john":1,"stat.leaveGame":6,"stat.useItem.minecraft.diamond_axe":4,"stat.jump":134,"stat.fallOneCm":2203,"stat.useItem.minecraft.stone_axe":36,"stat.crouchOneCm":2751,"stat.pickup.minecraft.dirt":4,"stat.useItem.minecraft.dirt":3,"stat.useItem.minecraft.stone_slab2":2,"stat.craftingTableInteraction":6,"stat.craftItem.minecraft.stone_axe":1,"stat.mineBlock.minecraft.leaves2":1,"stat.mineBlock.minecraft.log2":20,"stat.pickup.minecraft.leather":14,"stat.damageTaken":20,"stat.craftItem.minecraft.stone_pickaxe":1,"stat.useItem.minecraft.wooden_pickaxe":38,"stat.pickup.minecraft.cobblestone":37,"stat.pickup.minecraft.log2":20,"stat.flyOneCm":31350,"stat.pickup.minecraft.wheat_seeds":1,"stat.drop.minecraft.wheat_seeds":1,"stat.damageDealt":1940,"stat.timeSinceDeath":31032,"stat.killEntity.Cow":14,"stat.mineBlock.minecraft.dirt":4,"stat.useItem.minecraft.spawn_egg":2,"stat.craftItem.minecraft.wooden_pickaxe":1,"stat.walkOneCm":16981,"stat.pickup.minecraft.stick":1,"stat.pickup.minecraft.crafting_table":1,"stat.craftItem.minecraft.crafting_table":1,"stat.pickup.minecraft.beef":26,"stat.pickup.minecraft.chicken":1,"stat.sprintOneCm":20328,"stat.craftItem.minecraft.stick":8,"stat.craftItem.minecraft.planks":24,"stat.killEntity.Chicken":1,"stat.mineBlock.minecraft.crafting_table":1,"stat.mobKills":16,"stat.drop":1,"stat.mineBlock.minecraft.leaves":1,"stat.playOneMinute":31032,"stat.sneakTime":1697,"stat.mineBlock.minecraft.stone":37,"stat.mineBlock.minecraft.tallgrass":7}